<?xml version="1.0" encoding="utf-8"?>
<edmx:Edmx Version="4.0" xmlns:edmx="http://docs.oasis-open.org/odata/ns/edmx" xmlns="http://docs.oasis-open.org/odata/ns/edm">
    <edmx:Reference Uri="/sap/opu/odata/IWFND/CATALOGSERVICE;v=2/Vocabularies(TechnicalName='%2FIWBEP%2FVOC_COMMUNICATION',Version='0001',SAP__Origin='LOCAL')/$value">
        <edmx:Include Namespace="com.sap.vocabularies.Communication.v1" Alias="Communication"/>
    </edmx:Reference>
    <edmx:Reference Uri="/sap/opu/odata/IWFND/CATALOGSERVICE;v=2/Vocabularies(TechnicalName='%2FIWBEP%2FVOC_PERSONALDATA',Version='0001',SAP__Origin='LOCAL')/$value">
        <edmx:Include Namespace="com.sap.vocabularies.PersonalData.v1" Alias="PersonalData"/>
    </edmx:Reference>
    <edmx:Reference Uri="/sap/opu/odata/IWFND/CATALOGSERVICE;v=2/Vocabularies(TechnicalName='%2FIWBEP%2FVOC_ANALYTICS',Version='0001',SAP__Origin='LOCAL')/$value">
        <edmx:Include Namespace="com.sap.vocabularies.Analytics.v1" Alias="Analytics"/>
    </edmx:Reference>
    <edmx:Reference Uri="/sap/opu/odata/IWFND/CATALOGSERVICE;v=2/Vocabularies(TechnicalName='%2FIWBEP%2FVOC_AGGREGATION',Version='0001',SAP__Origin='LOCAL')/$value">
        <edmx:Include Namespace="Org.OData.Aggregation.V1" Alias="SAP__aggregation"/>
    </edmx:Reference>
    <edmx:Reference Uri="/sap/opu/odata/IWFND/CATALOGSERVICE;v=2/Vocabularies(TechnicalName='%2FIWBEP%2FVOC_CAPABILITIES',Version='0001',SAP__Origin='LOCAL')/$value">
        <edmx:Include Namespace="Org.OData.Capabilities.V1" Alias="SAP__capabilities"/>
    </edmx:Reference>
    <edmx:Reference Uri="/sap/opu/odata/IWFND/CATALOGSERVICE;v=2/Vocabularies(TechnicalName='%2FIWBEP%2FVOC_CODELIST',Version='0001',SAP__Origin='LOCAL')/$value">
        <edmx:Include Namespace="com.sap.vocabularies.CodeList.v1" Alias="SAP__CodeList"/>
    </edmx:Reference>
    <edmx:Reference Uri="/sap/opu/odata/IWFND/CATALOGSERVICE;v=2/Vocabularies(TechnicalName='%2FIWBEP%2FVOC_COMMON',Version='0001',SAP__Origin='LOCAL')/$value">
        <edmx:Include Namespace="com.sap.vocabularies.Common.v1" Alias="SAP__common"/>
    </edmx:Reference>
    <edmx:Reference Uri="/sap/opu/odata/IWFND/CATALOGSERVICE;v=2/Vocabularies(TechnicalName='%2FIWBEP%2FVOC_CORE',Version='0001',SAP__Origin='LOCAL')/$value">
        <edmx:Include Namespace="Org.OData.Core.V1" Alias="SAP__core"/>
    </edmx:Reference>
    <edmx:Reference Uri="/sap/opu/odata/IWFND/CATALOGSERVICE;v=2/Vocabularies(TechnicalName='%2FIWBEP%2FVOC_HIERARCHY',Version='0001',SAP__Origin='LOCAL')/$value">
        <edmx:Include Namespace="com.sap.vocabularies.Hierarchy.v1" Alias="SAP__hierarchy"/>
    </edmx:Reference>
    <edmx:Reference Uri="/sap/opu/odata/IWFND/CATALOGSERVICE;v=2/Vocabularies(TechnicalName='%2FIWBEP%2FVOC_HTML5',Version='0001',SAP__Origin='LOCAL')/$value">
        <edmx:Include Namespace="com.sap.vocabularies.HTML5.v1" Alias="SAP__HTML5"/>
    </edmx:Reference>
    <edmx:Reference Uri="/sap/opu/odata/IWFND/CATALOGSERVICE;v=2/Vocabularies(TechnicalName='%2FIWBEP%2FVOC_MEASURES',Version='0001',SAP__Origin='LOCAL')/$value">
        <edmx:Include Namespace="Org.OData.Measures.V1" Alias="SAP__measures"/>
    </edmx:Reference>
    <edmx:Reference Uri="/sap/opu/odata/IWFND/CATALOGSERVICE;v=2/Vocabularies(TechnicalName='%2FIWBEP%2FVOC_ODM',Version='0001',SAP__Origin='LOCAL')/$value">
        <edmx:Include Namespace="com.sap.vocabularies.ODM.v1" Alias="SAP__ODM"/>
    </edmx:Reference>
    <edmx:Reference Uri="/sap/opu/odata/IWFND/CATALOGSERVICE;v=2/Vocabularies(TechnicalName='%2FIWBEP%2FVOC_PDF',Version='0001',SAP__Origin='LOCAL')/$value">
        <edmx:Include Namespace="com.sap.vocabularies.PDF.v1" Alias="SAP__PDF"/>
    </edmx:Reference>
    <edmx:Reference Uri="/sap/opu/odata/IWFND/CATALOGSERVICE;v=2/Vocabularies(TechnicalName='%2FIWBEP%2FVOC_SESSION',Version='0001',SAP__Origin='LOCAL')/$value">
        <edmx:Include Namespace="com.sap.vocabularies.Session.v1" Alias="SAP__session"/>
    </edmx:Reference>
    <edmx:Reference Uri="/sap/opu/odata/IWFND/CATALOGSERVICE;v=2/Vocabularies(TechnicalName='%2FIWBEP%2FVOC_UI',Version='0001',SAP__Origin='LOCAL')/$value">
        <edmx:Include Namespace="com.sap.vocabularies.UI.v1" Alias="SAP__UI"/>
    </edmx:Reference>
    <edmx:Reference Uri="/sap/opu/odata/IWFND/CATALOGSERVICE;v=2/Vocabularies(TechnicalName='%2FIWBEP%2FVOC_VALIDATION',Version='0001',SAP__Origin='LOCAL')/$value">
        <edmx:Include Namespace="Org.OData.Validation.V1" Alias="SAP__validation"/>
    </edmx:Reference>
    <edmx:DataServices>
        <Schema Namespace="com.sap.gateway.srvd.zui_tbcat_rev_cfi000_o4.v0001" Alias="SAP__self">
            <Annotation Term="SAP__core.SchemaVersion" String="1.0.0"/>
            <EntityType Name="I_DraftAdministrativeDataType">
                <Key>
                    <PropertyRef Name="DraftUUID"/>
                    <PropertyRef Name="DraftEntityType"/>
                </Key>
                <Property Name="DraftUUID" Type="Edm.Guid" Nullable="false"/>
                <Property Name="DraftEntityType" Type="Edm.String" Nullable="false" MaxLength="30"/>
                <Property Name="CreationDateTime" Type="Edm.DateTimeOffset" Precision="7"/>
                <Property Name="CreatedByUser" Type="Edm.String" Nullable="false" MaxLength="12"/>
                <Property Name="LastChangeDateTime" Type="Edm.DateTimeOffset" Precision="7"/>
                <Property Name="LastChangedByUser" Type="Edm.String" Nullable="false" MaxLength="12"/>
                <Property Name="DraftAccessType" Type="Edm.String" Nullable="false" MaxLength="1"/>
                <Property Name="ProcessingStartDateTime" Type="Edm.DateTimeOffset" Precision="7"/>
                <Property Name="InProcessByUser" Type="Edm.String" Nullable="false" MaxLength="12"/>
                <Property Name="DraftIsKeptByUser" Type="Edm.Boolean" Nullable="false"/>
                <Property Name="EnqueueStartDateTime" Type="Edm.DateTimeOffset" Precision="7"/>
                <Property Name="DraftIsCreatedByMe" Type="Edm.Boolean" Nullable="false"/>
                <Property Name="DraftIsLastChangedByMe" Type="Edm.Boolean" Nullable="false"/>
                <Property Name="DraftIsProcessedByMe" Type="Edm.Boolean" Nullable="false"/>
                <Property Name="CreatedByUserDescription" Type="Edm.String" Nullable="false" MaxLength="80"/>
                <Property Name="LastChangedByUserDescription" Type="Edm.String" Nullable="false" MaxLength="80"/>
                <Property Name="InProcessByUserDescription" Type="Edm.String" Nullable="false" MaxLength="80"/>
            </EntityType>
            <EntityType Name="ZC_TBCAT_REV_CFI000Type">
                <Key>
                    <PropertyRef Name="Idtype"/>
                    <PropertyRef Name="Itemtype"/>
                    <PropertyRef Name="Baseitem"/>
                    <PropertyRef Name="Sequenceno"/>
                    <PropertyRef Name="IsActiveEntity"/>
                </Key>
                <Property Name="Idtype" Type="Edm.String" Nullable="false" MaxLength="10"/>
                <Property Name="Itemtype" Type="Edm.String" Nullable="false" MaxLength="30"/>
                <Property Name="Baseitem" Type="Edm.String" Nullable="false" MaxLength="20"/>
                <Property Name="Sequenceno" Type="Edm.Decimal" Nullable="false" Precision="1"/>
                <Property Name="Glaccount" Type="Edm.String" Nullable="false" MaxLength="20"/>
                <Property Name="Debitcreditcode" Type="Edm.String" Nullable="false" MaxLength="1"/>
                <Property Name="Posneg" Type="Edm.String" Nullable="false" MaxLength="5"/>
                <Property Name="Amountintransactioncurrency" Type="Edm.String" Nullable="false" MaxLength="50"/>
                <Property Name="Amountincompanycodecurrency" Type="Edm.String" Nullable="false" MaxLength="50"/>
                <Property Name="Quantityinentryunit" Type="Edm.String" Nullable="false" MaxLength="50"/>
                <Property Name="Assignmentreference" Type="Edm.String" Nullable="false" MaxLength="50"/>
                <Property Name="Housebank" Type="Edm.String" Nullable="false" MaxLength="10"/>
                <Property Name="Housebankaccount" Type="Edm.String" Nullable="false" MaxLength="10"/>
                <Property Name="Documentitemtext" Type="Edm.String" Nullable="false" MaxLength="50"/>
                <Property Name="Reference1idbybusinesspartner" Type="Edm.String" Nullable="false" MaxLength="50"/>
                <Property Name="Reference2idbybusinesspartner" Type="Edm.String" Nullable="false" MaxLength="50"/>
                <Property Name="Reference3idbybusinesspartner" Type="Edm.String" Nullable="false" MaxLength="50"/>
                <Property Name="Accountassignmenttype" Type="Edm.String" Nullable="false" MaxLength="5"/>
                <Property Name="Profitcenter" Type="Edm.String" Nullable="false" MaxLength="10"/>
                <Property Name="Costcenter" Type="Edm.String" Nullable="false" MaxLength="10"/>
                <Property Name="Tariffcode" Type="Edm.String" Nullable="false" MaxLength="50"/>
                <Property Name="Lineofservice" Type="Edm.String" Nullable="false" MaxLength="50"/>
                <Property Name="Ship" Type="Edm.String" Nullable="false" MaxLength="50"/>
                <Property Name="Paymentmethod" Type="Edm.String" Nullable="false" MaxLength="50"/>
                <Property Name="Taxitemclassification" Type="Edm.String" Nullable="false" MaxLength="5"/>
                <Property Name="Createdby" Type="Edm.String" Nullable="false" MaxLength="12"/>
                <Property Name="LocalLastChangedAt" Type="Edm.DateTimeOffset" Precision="7"/>
                <Property Name="LastChangedAt" Type="Edm.DateTimeOffset" Precision="7"/>
                <Property Name="LastChangedBy" Type="Edm.String" Nullable="false" MaxLength="12"/>
                <Property Name="HasDraftEntity" Type="Edm.Boolean" Nullable="false"/>
                <Property Name="DraftEntityCreationDateTime" Type="Edm.DateTimeOffset" Precision="7"/>
                <Property Name="DraftEntityLastChangeDateTime" Type="Edm.DateTimeOffset" Precision="7"/>
                <Property Name="HasActiveEntity" Type="Edm.Boolean" Nullable="false"/>
                <Property Name="IsActiveEntity" Type="Edm.Boolean" Nullable="false"/>
                <Property Name="__EntityControl" Type="com.sap.gateway.srvd.zui_tbcat_rev_cfi000_o4.v0001.EntityControl"/>
                <Property Name="__OperationControl" Type="com.sap.gateway.srvd.zui_tbcat_rev_cfi000_o4.v0001.ZC_TBCAT_REV_CFI000OperationControl"/>
                <Property Name="SAP__Messages" Type="Collection(com.sap.gateway.srvd.zui_tbcat_rev_cfi000_o4.v0001.SAP__Message)" Nullable="false"/>
                <NavigationProperty Name="DraftAdministrativeData" Type="com.sap.gateway.srvd.zui_tbcat_rev_cfi000_o4.v0001.I_DraftAdministrativeDataType"/>
                <NavigationProperty Name="SiblingEntity" Type="com.sap.gateway.srvd.zui_tbcat_rev_cfi000_o4.v0001.ZC_TBCAT_REV_CFI000Type"/>
            </EntityType>
            <ComplexType Name="ZC_TBCAT_REV_CFI000OperationControl">
                <Property Name="Edit" Type="Edm.Boolean" Nullable="false"/>
            </ComplexType>
            <ComplexType Name="EntityControl">
                <Property Name="Deletable" Type="Edm.Boolean" Nullable="false"/>
                <Property Name="Updatable" Type="Edm.Boolean" Nullable="false"/>
            </ComplexType>
            <ComplexType Name="SAP__Message">
                <Property Name="code" Type="Edm.String" Nullable="false"/>
                <Property Name="message" Type="Edm.String" Nullable="false"/>
                <Property Name="target" Type="Edm.String"/>
                <Property Name="additionalTargets" Type="Collection(Edm.String)" Nullable="false"/>
                <Property Name="transition" Type="Edm.Boolean" Nullable="false"/>
                <Property Name="numericSeverity" Type="Edm.Byte" Nullable="false"/>
                <Property Name="longtextUrl" Type="Edm.String"/>
            </ComplexType>
            <Action Name="Discard" IsBound="true">
                <Parameter Name="_it" Type="com.sap.gateway.srvd.zui_tbcat_rev_cfi000_o4.v0001.ZC_TBCAT_REV_CFI000Type" Nullable="false"/>
            </Action>
            <Action Name="Prepare" IsBound="true">
                <Parameter Name="_it" Type="com.sap.gateway.srvd.zui_tbcat_rev_cfi000_o4.v0001.ZC_TBCAT_REV_CFI000Type" Nullable="false"/>
            </Action>
            <Action Name="Resume" IsBound="true">
                <Parameter Name="_it" Type="com.sap.gateway.srvd.zui_tbcat_rev_cfi000_o4.v0001.ZC_TBCAT_REV_CFI000Type" Nullable="false"/>
            </Action>
            <Action Name="Activate" EntitySetPath="_it" IsBound="true">
                <Parameter Name="_it" Type="com.sap.gateway.srvd.zui_tbcat_rev_cfi000_o4.v0001.ZC_TBCAT_REV_CFI000Type" Nullable="false"/>
                <ReturnType Type="com.sap.gateway.srvd.zui_tbcat_rev_cfi000_o4.v0001.ZC_TBCAT_REV_CFI000Type" Nullable="false"/>
            </Action>
            <Action Name="Edit" EntitySetPath="_it" IsBound="true">
                <Parameter Name="_it" Type="com.sap.gateway.srvd.zui_tbcat_rev_cfi000_o4.v0001.ZC_TBCAT_REV_CFI000Type" Nullable="false"/>
                <Parameter Name="PreserveChanges" Type="Edm.Boolean" Nullable="false"/>
                <ReturnType Type="com.sap.gateway.srvd.zui_tbcat_rev_cfi000_o4.v0001.ZC_TBCAT_REV_CFI000Type" Nullable="false"/>
            </Action>
            <EntityContainer Name="Container">
                <EntitySet Name="I_DraftAdministrativeData" EntityType="com.sap.gateway.srvd.zui_tbcat_rev_cfi000_o4.v0001.I_DraftAdministrativeDataType"/>
                <EntitySet Name="ZC_TBCAT_REV_CFI000" EntityType="com.sap.gateway.srvd.zui_tbcat_rev_cfi000_o4.v0001.ZC_TBCAT_REV_CFI000Type">
                    <NavigationPropertyBinding Path="DraftAdministrativeData" Target="I_DraftAdministrativeData"/>
                    <NavigationPropertyBinding Path="SiblingEntity" Target="ZC_TBCAT_REV_CFI000"/>
                </EntitySet>
            </EntityContainer>
            <Annotations Target="SAP__self.I_DraftAdministrativeDataType/DraftEntityType">
                <Annotation Term="SAP__common.IsUpperCase"/>
                <Annotation Term="SAP__UI.Hidden"/>
                <Annotation Term="SAP__common.Label" String="Draft Entity ID"/>
            </Annotations>
            <Annotations Target="SAP__self.I_DraftAdministrativeDataType/CreatedByUser">
                <Annotation Term="SAP__common.Text" Path="CreatedByUserDescription"/>
                <Annotation Term="SAP__common.IsUpperCase"/>
                <Annotation Term="SAP__common.ValueListReferences">
                    <Collection>
                        <String>../../../../srvd_f4/sap/i_draftadministrativeuservh/0001;ps='srvd-zui_tbcat_rev_cfi000_o4-0001';va='com.sap.gateway.srvd.zui_tbcat_rev_cfi000_o4.v0001.et-i_draftadministrativedata.createdbyuser'/$metadata</String>
                    </Collection>
                </Annotation>
                <Annotation Term="SAP__common.Label" String="Draft Created By"/>
            </Annotations>
            <Annotations Target="SAP__self.I_DraftAdministrativeDataType/LastChangedByUser">
                <Annotation Term="SAP__common.Text" Path="LastChangedByUserDescription"/>
                <Annotation Term="SAP__common.IsUpperCase"/>
                <Annotation Term="SAP__common.ValueListReferences">
                    <Collection>
                        <String>../../../../srvd_f4/sap/i_draftadministrativeuservh/0001;ps='srvd-zui_tbcat_rev_cfi000_o4-0001';va='com.sap.gateway.srvd.zui_tbcat_rev_cfi000_o4.v0001.et-i_draftadministrativedata.lastchangedbyuser'/$metadata</String>
                    </Collection>
                </Annotation>
                <Annotation Term="SAP__common.Label" String="Draft Last Changed By"/>
            </Annotations>
            <Annotations Target="SAP__self.I_DraftAdministrativeDataType/DraftAccessType">
                <Annotation Term="SAP__common.IsUpperCase"/>
                <Annotation Term="SAP__UI.Hidden"/>
                <Annotation Term="SAP__common.Label" String="Draft Access Type"/>
            </Annotations>
            <Annotations Target="SAP__self.I_DraftAdministrativeDataType/InProcessByUser">
                <Annotation Term="SAP__common.Text" Path="InProcessByUserDescription"/>
                <Annotation Term="SAP__common.IsUpperCase"/>
                <Annotation Term="SAP__UI.Hidden"/>
                <Annotation Term="SAP__common.Label" String="Draft In Process By"/>
            </Annotations>
            <Annotations Target="SAP__self.I_DraftAdministrativeDataType">
                <Annotation Term="SAP__common.Label" String="Draft Administration Data"/>
            </Annotations>
            <Annotations Target="SAP__self.Container/I_DraftAdministrativeData">
                <Annotation Term="SAP__capabilities.SearchRestrictions">
                    <Record>
                        <PropertyValue Property="Searchable" Bool="true"/>
                        <PropertyValue Property="UnsupportedExpressions" EnumMember="SAP__capabilities.SearchExpressions/AND SAP__capabilities.SearchExpressions/NOT SAP__capabilities.SearchExpressions/group "/>
                        <PropertyValue Property="SearchSyntax" String="https://url.sap/odata-search"/>
                    </Record>
                </Annotation>
                <Annotation Term="SAP__capabilities.FilterRestrictions">
                    <Record>
                        <PropertyValue Property="Filterable" Bool="true"/>
                        <PropertyValue Property="FilterExpressionRestrictions">
                            <Collection>
                                <Record>
                                    <PropertyValue Property="Property" PropertyPath="CreationDateTime"/>
                                    <PropertyValue Property="AllowedExpressions" String="SingleRange"/>
                                </Record>
                                <Record>
                                    <PropertyValue Property="Property" PropertyPath="LastChangeDateTime"/>
                                    <PropertyValue Property="AllowedExpressions" String="SingleRange"/>
                                </Record>
                            </Collection>
                        </PropertyValue>
                    </Record>
                </Annotation>
                <Annotation Term="SAP__capabilities.ReadRestrictions">
                    <Record>
                        <PropertyValue Property="Readable" Bool="false"/>
                    </Record>
                </Annotation>
                <Annotation Term="SAP__capabilities.InsertRestrictions">
                    <Record>
                        <PropertyValue Property="Insertable" Bool="false"/>
                    </Record>
                </Annotation>
                <Annotation Term="SAP__capabilities.DeleteRestrictions">
                    <Record>
                        <PropertyValue Property="Deletable" Bool="false"/>
                    </Record>
                </Annotation>
                <Annotation Term="SAP__capabilities.UpdateRestrictions">
                    <Record>
                        <PropertyValue Property="Updatable" Bool="false"/>
                        <PropertyValue Property="QueryOptions">
                            <Record>
                                <PropertyValue Property="SelectSupported" Bool="true"/>
                            </Record>
                        </PropertyValue>
                    </Record>
                </Annotation>
            </Annotations>
            <Annotations Target="SAP__self.ZC_TBCAT_REV_CFI000Type/Idtype">
                <Annotation Term="SAP__core.Immutable"/>
                <Annotation Term="SAP__common.Label" String="Idtype"/>
                <Annotation Term="SAP__common.QuickInfo" String="IDTYPE"/>
            </Annotations>
            <Annotations Target="SAP__self.ZC_TBCAT_REV_CFI000Type/Itemtype">
                <Annotation Term="SAP__core.Immutable"/>
                <Annotation Term="SAP__common.Label" String="Itemtype"/>
            </Annotations>
            <Annotations Target="SAP__self.ZC_TBCAT_REV_CFI000Type/Baseitem">
                <Annotation Term="SAP__core.Immutable"/>
                <Annotation Term="SAP__common.Label" String="Baseitem"/>
            </Annotations>
            <Annotations Target="SAP__self.ZC_TBCAT_REV_CFI000Type/Sequenceno">
                <Annotation Term="SAP__core.Immutable"/>
                <Annotation Term="SAP__common.Label" String="Sequenceno"/>
            </Annotations>
            <Annotations Target="SAP__self.ZC_TBCAT_REV_CFI000Type/Debitcreditcode">
                <Annotation Term="SAP__common.IsUpperCase"/>
                <Annotation Term="SAP__common.Label" String="Debit/Credit Ind."/>
                <Annotation Term="SAP__common.Heading" String="D/C"/>
                <Annotation Term="SAP__common.QuickInfo" String="Debit/Credit Indicator"/>
                <Annotation Term="SAP__common.DocumentationRef" String="urn:sap-com:documentation:key?=type=DE&amp;id=SHKZG"/>
            </Annotations>
            <Annotations Target="SAP__self.ZC_TBCAT_REV_CFI000Type/Profitcenter">
                <Annotation Term="SAP__common.IsUpperCase"/>
                <Annotation Term="SAP__common.Label" String="Profit Center"/>
                <Annotation Term="SAP__common.Heading" String="Profit Ctr"/>
                <Annotation Term="SAP__common.DocumentationRef" String="urn:sap-com:documentation:key?=type=DE&amp;id=PRCTR"/>
            </Annotations>
            <Annotations Target="SAP__self.ZC_TBCAT_REV_CFI000Type/Costcenter">
                <Annotation Term="SAP__common.IsUpperCase"/>
                <Annotation Term="SAP__common.Label" String="Cost Center"/>
                <Annotation Term="SAP__common.Heading" String="Cost Ctr"/>
                <Annotation Term="SAP__common.DocumentationRef" String="urn:sap-com:documentation:key?=type=DE&amp;id=KOSTL"/>
            </Annotations>
            <Annotations Target="SAP__self.ZC_TBCAT_REV_CFI000Type/Createdby">
                <Annotation Term="SAP__core.Computed"/>
                <Annotation Term="SAP__common.IsUpperCase"/>
                <Annotation Term="SAP__common.Label" String="Created By"/>
                <Annotation Term="SAP__common.QuickInfo" String="Created By User"/>
                <Annotation Term="SAP__common.DocumentationRef" String="urn:sap-com:documentation:key?=type=DE&amp;id=ABP_CREATION_USER"/>
            </Annotations>
            <Annotations Target="SAP__self.ZC_TBCAT_REV_CFI000Type">
                <Annotation Term="SAP__common.CreatedBy" Path="Createdby"/>
                <Annotation Term="SAP__common.ChangedAt" Path="LastChangedAt"/>
                <Annotation Term="SAP__common.Label" String="###GENERATED Core Data Service Entity"/>
                <Annotation Term="SAP__common.SAPObjectNodeType">
                    <Record>
                        <PropertyValue Property="Name" String="ZTBCAT_REV_CFI000"/>
                    </Record>
                </Annotation>
                <Annotation Term="SAP__UI.Facets">
                    <Collection>
                        <Record Type="SAP__UI.ReferenceFacet">
                            <PropertyValue Property="Label" String="General Information"/>
                            <PropertyValue Property="ID" String="GeneralInfo"/>
                            <PropertyValue Property="Target" AnnotationPath="@SAP__UI.Identification"/>
                        </Record>
                    </Collection>
                </Annotation>
                <Annotation Term="SAP__UI.HeaderInfo">
                    <Annotation Term="SAP__core.Messages">
                        <Collection>
                            <Record>
                                <PropertyValue Property="message" String="UI.HEADERINFO: TypeNamePlural is mandatory"/>
                                <PropertyValue Property="severity" String="error"/>
                            </Record>
                        </Collection>
                    </Annotation>
                    <Record>
                        <PropertyValue Property="TypeName" String="###GENERATED Core Data Service Entity"/>
                        <PropertyValue Property="Title">
                            <Record Type="SAP__UI.DataField">
                                <PropertyValue Property="Value" Path="Idtype"/>
                            </Record>
                        </PropertyValue>
                        <PropertyValue Property="Description">
                            <Record Type="SAP__UI.DataField">
                                <PropertyValue Property="Value" Path="Idtype"/>
                            </Record>
                        </PropertyValue>
                    </Record>
                </Annotation>
                <Annotation Term="SAP__UI.Identification">
                    <Collection>
                        <Record Type="SAP__UI.DataField">
                            <PropertyValue Property="Value" Path="Idtype"/>
                        </Record>
                        <Record Type="SAP__UI.DataField">
                            <PropertyValue Property="Value" Path="Itemtype"/>
                        </Record>
                        <Record Type="SAP__UI.DataField">
                            <PropertyValue Property="Value" Path="Baseitem"/>
                        </Record>
                        <Record Type="SAP__UI.DataField">
                            <PropertyValue Property="Value" Path="Sequenceno"/>
                        </Record>
                        <Record Type="SAP__UI.DataField">
                            <PropertyValue Property="Value" Path="Glaccount"/>
                        </Record>
                        <Record Type="SAP__UI.DataField">
                            <PropertyValue Property="Value" Path="Debitcreditcode"/>
                        </Record>
                        <Record Type="SAP__UI.DataField">
                            <PropertyValue Property="Value" Path="Posneg"/>
                        </Record>
                        <Record Type="SAP__UI.DataField">
                            <PropertyValue Property="Value" Path="Amountintransactioncurrency"/>
                        </Record>
                        <Record Type="SAP__UI.DataField">
                            <PropertyValue Property="Value" Path="Amountincompanycodecurrency"/>
                        </Record>
                        <Record Type="SAP__UI.DataField">
                            <PropertyValue Property="Value" Path="Quantityinentryunit"/>
                        </Record>
                        <Record Type="SAP__UI.DataField">
                            <PropertyValue Property="Value" Path="Assignmentreference"/>
                        </Record>
                        <Record Type="SAP__UI.DataField">
                            <PropertyValue Property="Value" Path="Housebank"/>
                        </Record>
                        <Record Type="SAP__UI.DataField">
                            <PropertyValue Property="Value" Path="Housebankaccount"/>
                        </Record>
                        <Record Type="SAP__UI.DataField">
                            <PropertyValue Property="Value" Path="Documentitemtext"/>
                        </Record>
                        <Record Type="SAP__UI.DataField">
                            <PropertyValue Property="Value" Path="Reference1idbybusinesspartner"/>
                        </Record>
                        <Record Type="SAP__UI.DataField">
                            <PropertyValue Property="Value" Path="Reference2idbybusinesspartner"/>
                        </Record>
                        <Record Type="SAP__UI.DataField">
                            <PropertyValue Property="Value" Path="Reference3idbybusinesspartner"/>
                        </Record>
                        <Record Type="SAP__UI.DataField">
                            <PropertyValue Property="Value" Path="Accountassignmenttype"/>
                        </Record>
                        <Record Type="SAP__UI.DataField">
                            <PropertyValue Property="Value" Path="Profitcenter"/>
                        </Record>
                        <Record Type="SAP__UI.DataField">
                            <PropertyValue Property="Value" Path="Costcenter"/>
                        </Record>
                        <Record Type="SAP__UI.DataField">
                            <PropertyValue Property="Value" Path="Tariffcode"/>
                        </Record>
                        <Record Type="SAP__UI.DataField">
                            <PropertyValue Property="Value" Path="Lineofservice"/>
                        </Record>
                        <Record Type="SAP__UI.DataField">
                            <PropertyValue Property="Value" Path="Ship"/>
                        </Record>
                        <Record Type="SAP__UI.DataField">
                            <PropertyValue Property="Value" Path="Paymentmethod"/>
                        </Record>
                        <Record Type="SAP__UI.DataField">
                            <PropertyValue Property="Value" Path="Taxitemclassification"/>
                        </Record>
                        <Record Type="SAP__UI.DataField">
                            <PropertyValue Property="Value" Path="Createdby"/>
                        </Record>
                        <Record Type="SAP__UI.DataField">
                            <PropertyValue Property="Value" Path="LocalLastChangedAt"/>
                        </Record>
                        <Record Type="SAP__UI.DataField">
                            <PropertyValue Property="Value" Path="LastChangedAt"/>
                        </Record>
                        <Record Type="SAP__UI.DataField">
                            <PropertyValue Property="Value" Path="LastChangedBy"/>
                        </Record>
                    </Collection>
                </Annotation>
                <Annotation Term="SAP__UI.LineItem">
                    <Collection>
                        <Record Type="SAP__UI.DataField">
                            <PropertyValue Property="Value" Path="Idtype"/>
                        </Record>
                        <Record Type="SAP__UI.DataField">
                            <PropertyValue Property="Value" Path="Itemtype"/>
                        </Record>
                        <Record Type="SAP__UI.DataField">
                            <PropertyValue Property="Value" Path="Baseitem"/>
                        </Record>
                        <Record Type="SAP__UI.DataField">
                            <PropertyValue Property="Value" Path="Sequenceno"/>
                        </Record>
                        <Record Type="SAP__UI.DataField">
                            <PropertyValue Property="Value" Path="Glaccount"/>
                        </Record>
                        <Record Type="SAP__UI.DataField">
                            <PropertyValue Property="Value" Path="Debitcreditcode"/>
                        </Record>
                        <Record Type="SAP__UI.DataField">
                            <PropertyValue Property="Value" Path="Posneg"/>
                        </Record>
                        <Record Type="SAP__UI.DataField">
                            <PropertyValue Property="Value" Path="Amountintransactioncurrency"/>
                        </Record>
                        <Record Type="SAP__UI.DataField">
                            <PropertyValue Property="Value" Path="Amountincompanycodecurrency"/>
                        </Record>
                        <Record Type="SAP__UI.DataField">
                            <PropertyValue Property="Value" Path="Quantityinentryunit"/>
                        </Record>
                        <Record Type="SAP__UI.DataField">
                            <PropertyValue Property="Value" Path="Assignmentreference"/>
                        </Record>
                        <Record Type="SAP__UI.DataField">
                            <PropertyValue Property="Value" Path="Housebank"/>
                        </Record>
                        <Record Type="SAP__UI.DataField">
                            <PropertyValue Property="Value" Path="Housebankaccount"/>
                        </Record>
                        <Record Type="SAP__UI.DataField">
                            <PropertyValue Property="Value" Path="Documentitemtext"/>
                        </Record>
                        <Record Type="SAP__UI.DataField">
                            <PropertyValue Property="Value" Path="Reference1idbybusinesspartner"/>
                        </Record>
                        <Record Type="SAP__UI.DataField">
                            <PropertyValue Property="Value" Path="Reference2idbybusinesspartner"/>
                        </Record>
                        <Record Type="SAP__UI.DataField">
                            <PropertyValue Property="Value" Path="Reference3idbybusinesspartner"/>
                        </Record>
                        <Record Type="SAP__UI.DataField">
                            <PropertyValue Property="Value" Path="Accountassignmenttype"/>
                        </Record>
                        <Record Type="SAP__UI.DataField">
                            <PropertyValue Property="Value" Path="Profitcenter"/>
                        </Record>
                        <Record Type="SAP__UI.DataField">
                            <PropertyValue Property="Value" Path="Costcenter"/>
                        </Record>
                        <Record Type="SAP__UI.DataField">
                            <PropertyValue Property="Value" Path="Tariffcode"/>
                        </Record>
                        <Record Type="SAP__UI.DataField">
                            <PropertyValue Property="Value" Path="Lineofservice"/>
                        </Record>
                        <Record Type="SAP__UI.DataField">
                            <PropertyValue Property="Value" Path="Ship"/>
                        </Record>
                        <Record Type="SAP__UI.DataField">
                            <PropertyValue Property="Value" Path="Paymentmethod"/>
                        </Record>
                        <Record Type="SAP__UI.DataField">
                            <PropertyValue Property="Value" Path="Taxitemclassification"/>
                        </Record>
                        <Record Type="SAP__UI.DataField">
                            <PropertyValue Property="Value" Path="Createdby"/>
                        </Record>
                        <Record Type="SAP__UI.DataField">
                            <PropertyValue Property="Value" Path="LocalLastChangedAt"/>
                        </Record>
                        <Record Type="SAP__UI.DataField">
                            <PropertyValue Property="Value" Path="LastChangedAt"/>
                        </Record>
                        <Record Type="SAP__UI.DataField">
                            <PropertyValue Property="Value" Path="LastChangedBy"/>
                        </Record>
                    </Collection>
                </Annotation>
                <Annotation Term="SAP__UI.SelectionFields">
                    <Collection>
                        <PropertyPath>Idtype</PropertyPath>
                        <PropertyPath>Itemtype</PropertyPath>
                        <PropertyPath>Baseitem</PropertyPath>
                        <PropertyPath>Sequenceno</PropertyPath>
                        <PropertyPath>Glaccount</PropertyPath>
                        <PropertyPath>Debitcreditcode</PropertyPath>
                        <PropertyPath>Posneg</PropertyPath>
                        <PropertyPath>Amountintransactioncurrency</PropertyPath>
                        <PropertyPath>Amountincompanycodecurrency</PropertyPath>
                        <PropertyPath>Quantityinentryunit</PropertyPath>
                        <PropertyPath>Assignmentreference</PropertyPath>
                        <PropertyPath>Housebank</PropertyPath>
                        <PropertyPath>Housebankaccount</PropertyPath>
                        <PropertyPath>Documentitemtext</PropertyPath>
                        <PropertyPath>Reference1idbybusinesspartner</PropertyPath>
                        <PropertyPath>Reference2idbybusinesspartner</PropertyPath>
                        <PropertyPath>Reference3idbybusinesspartner</PropertyPath>
                        <PropertyPath>Accountassignmenttype</PropertyPath>
                        <PropertyPath>Profitcenter</PropertyPath>
                        <PropertyPath>Costcenter</PropertyPath>
                        <PropertyPath>Tariffcode</PropertyPath>
                        <PropertyPath>Lineofservice</PropertyPath>
                        <PropertyPath>Ship</PropertyPath>
                        <PropertyPath>Paymentmethod</PropertyPath>
                        <PropertyPath>Taxitemclassification</PropertyPath>
                        <PropertyPath>Createdby</PropertyPath>
                        <PropertyPath>LocalLastChangedAt</PropertyPath>
                        <PropertyPath>LastChangedAt</PropertyPath>
                        <PropertyPath>LastChangedBy</PropertyPath>
                    </Collection>
                </Annotation>
                <Annotation Term="SAP__common.Messages" Path="SAP__Messages"/>
            </Annotations>
            <Annotations Target="SAP__self.ZC_TBCAT_REV_CFI000Type/LocalLastChangedAt">
                <Annotation Term="SAP__core.Computed"/>
                <Annotation Term="SAP__common.Label" String="Changed On"/>
                <Annotation Term="SAP__common.QuickInfo" String="Local Instance Last Change Date Time"/>
                <Annotation Term="SAP__common.DocumentationRef" String="urn:sap-com:documentation:key?=type=DE&amp;id=ABP_LOCINST_LASTCHANGE_TSTMPL"/>
            </Annotations>
            <Annotations Target="SAP__self.ZC_TBCAT_REV_CFI000Type/LastChangedAt">
                <Annotation Term="SAP__core.Computed"/>
                <Annotation Term="SAP__common.Label" String="Changed On"/>
                <Annotation Term="SAP__common.QuickInfo" String="Last Change Date Time"/>
                <Annotation Term="SAP__common.DocumentationRef" String="urn:sap-com:documentation:key?=type=DE&amp;id=ABP_LASTCHANGE_TSTMPL"/>
            </Annotations>
            <Annotations Target="SAP__self.ZC_TBCAT_REV_CFI000Type/LastChangedBy">
                <Annotation Term="SAP__core.Computed"/>
                <Annotation Term="SAP__common.IsUpperCase"/>
                <Annotation Term="SAP__common.Label" String="Changed By"/>
                <Annotation Term="SAP__common.QuickInfo" String="Local Instance Last Changed By User"/>
                <Annotation Term="SAP__common.DocumentationRef" String="urn:sap-com:documentation:key?=type=DE&amp;id=ABP_LOCINST_LASTCHANGE_USER"/>
            </Annotations>
            <Annotations Target="SAP__self.ZC_TBCAT_REV_CFI000Type/HasDraftEntity">
                <Annotation Term="SAP__core.Computed"/>
                <Annotation Term="SAP__UI.HiddenFilter"/>
                <Annotation Term="SAP__UI.Hidden"/>
                <Annotation Term="SAP__common.Label" String="Has Draft"/>
                <Annotation Term="SAP__common.QuickInfo" String="Draft - Indicator - Has draft document"/>
            </Annotations>
            <Annotations Target="SAP__self.ZC_TBCAT_REV_CFI000Type/DraftEntityCreationDateTime">
                <Annotation Term="SAP__core.Computed"/>
                <Annotation Term="SAP__UI.HiddenFilter"/>
                <Annotation Term="SAP__UI.Hidden"/>
                <Annotation Term="SAP__common.Label" String="Draft Created On"/>
            </Annotations>
            <Annotations Target="SAP__self.ZC_TBCAT_REV_CFI000Type/DraftEntityLastChangeDateTime">
                <Annotation Term="SAP__core.Computed"/>
                <Annotation Term="SAP__UI.HiddenFilter"/>
                <Annotation Term="SAP__UI.Hidden"/>
                <Annotation Term="SAP__common.Label" String="Draft Last Changed On"/>
            </Annotations>
            <Annotations Target="SAP__self.ZC_TBCAT_REV_CFI000Type/HasActiveEntity">
                <Annotation Term="SAP__core.Computed"/>
                <Annotation Term="SAP__UI.HiddenFilter"/>
                <Annotation Term="SAP__UI.Hidden"/>
                <Annotation Term="SAP__common.Label" String="Has active"/>
                <Annotation Term="SAP__common.QuickInfo" String="Draft - Indicator - Has active document"/>
            </Annotations>
            <Annotations Target="SAP__self.ZC_TBCAT_REV_CFI000Type/IsActiveEntity">
                <Annotation Term="SAP__core.Computed"/>
                <Annotation Term="SAP__UI.HiddenFilter"/>
                <Annotation Term="SAP__UI.Hidden"/>
                <Annotation Term="SAP__common.Label" String="Is active"/>
                <Annotation Term="SAP__common.QuickInfo" String="Draft - Indicator - Is active document"/>
            </Annotations>
            <Annotations Target="SAP__self.ZC_TBCAT_REV_CFI000Type/__EntityControl">
                <Annotation Term="SAP__core.Computed"/>
                <Annotation Term="SAP__UI.HiddenFilter"/>
                <Annotation Term="SAP__UI.Hidden"/>
            </Annotations>
            <Annotations Target="SAP__self.ZC_TBCAT_REV_CFI000Type/__OperationControl">
                <Annotation Term="SAP__core.Computed"/>
                <Annotation Term="SAP__UI.HiddenFilter"/>
                <Annotation Term="SAP__UI.Hidden"/>
            </Annotations>
            <Annotations Target="SAP__self.Container/ZC_TBCAT_REV_CFI000">
                <Annotation Term="SAP__common.DraftRoot">
                    <Record>
                        <PropertyValue Property="DiscardAction" String="com.sap.gateway.srvd.zui_tbcat_rev_cfi000_o4.v0001.Discard"/>
                        <PropertyValue Property="PreparationAction" String="com.sap.gateway.srvd.zui_tbcat_rev_cfi000_o4.v0001.Prepare"/>
                        <PropertyValue Property="ActivationAction" String="com.sap.gateway.srvd.zui_tbcat_rev_cfi000_o4.v0001.Activate"/>
                        <PropertyValue Property="EditAction" String="com.sap.gateway.srvd.zui_tbcat_rev_cfi000_o4.v0001.Edit"/>
                    </Record>
                </Annotation>
                <Annotation Term="SAP__capabilities.SearchRestrictions">
                    <Record>
                        <PropertyValue Property="Searchable" Bool="false"/>
                    </Record>
                </Annotation>
                <Annotation Term="SAP__capabilities.FilterRestrictions">
                    <Record>
                        <PropertyValue Property="Filterable" Bool="true"/>
                        <PropertyValue Property="FilterExpressionRestrictions">
                            <Collection>
                                <Record>
                                    <PropertyValue Property="Property" PropertyPath="DraftEntityCreationDateTime"/>
                                    <PropertyValue Property="AllowedExpressions" String="SingleRange"/>
                                </Record>
                                <Record>
                                    <PropertyValue Property="Property" PropertyPath="DraftEntityLastChangeDateTime"/>
                                    <PropertyValue Property="AllowedExpressions" String="SingleRange"/>
                                </Record>
                            </Collection>
                        </PropertyValue>
                        <PropertyValue Property="NonFilterableProperties">
                            <Collection>
                                <PropertyPath>__EntityControl</PropertyPath>
                                <PropertyPath>__OperationControl</PropertyPath>
                            </Collection>
                        </PropertyValue>
                    </Record>
                </Annotation>
                <Annotation Term="SAP__capabilities.SortRestrictions">
                    <Record>
                        <PropertyValue Property="NonSortableProperties">
                            <Collection>
                                <PropertyPath>__EntityControl</PropertyPath>
                                <PropertyPath>__OperationControl</PropertyPath>
                            </Collection>
                        </PropertyValue>
                    </Record>
                </Annotation>
                <Annotation Term="SAP__capabilities.InsertRestrictions">
                    <Record>
                        <PropertyValue Property="RequiredProperties">
                            <Collection>
                                <PropertyPath>Idtype</PropertyPath>
                                <PropertyPath>Itemtype</PropertyPath>
                                <PropertyPath>Baseitem</PropertyPath>
                                <PropertyPath>Sequenceno</PropertyPath>
                            </Collection>
                        </PropertyValue>
                    </Record>
                </Annotation>
                <Annotation Term="SAP__capabilities.UpdateRestrictions">
                    <Record>
                        <PropertyValue Property="DeltaUpdateSupported" Bool="true"/>
                        <PropertyValue Property="NonUpdatableProperties">
                            <Collection>
                                <PropertyPath>Idtype</PropertyPath>
                                <PropertyPath>Itemtype</PropertyPath>
                                <PropertyPath>Baseitem</PropertyPath>
                                <PropertyPath>Sequenceno</PropertyPath>
                            </Collection>
                        </PropertyValue>
                        <PropertyValue Property="Updatable" Path="__EntityControl/Updatable"/>
                        <PropertyValue Property="NonUpdatableNavigationProperties">
                            <Collection>
                                <PropertyPath>DraftAdministrativeData</PropertyPath>
                                <PropertyPath>SiblingEntity</PropertyPath>
                            </Collection>
                        </PropertyValue>
                        <PropertyValue Property="QueryOptions">
                            <Record>
                                <PropertyValue Property="SelectSupported" Bool="true"/>
                            </Record>
                        </PropertyValue>
                    </Record>
                </Annotation>
                <Annotation Term="SAP__capabilities.DeepUpdateSupport">
                    <Record>
                        <PropertyValue Property="ContentIDSupported" Bool="true"/>
                    </Record>
                </Annotation>
                <Annotation Term="SAP__capabilities.DeleteRestrictions">
                    <Record>
                        <PropertyValue Property="Deletable" Path="__EntityControl/Deletable"/>
                    </Record>
                </Annotation>
                <Annotation Term="SAP__core.OptimisticConcurrency">
                    <Collection>
                        <PropertyPath>LocalLastChangedAt</PropertyPath>
                    </Collection>
                </Annotation>
            </Annotations>
            <Annotations Target="SAP__self.Edit(SAP__self.ZC_TBCAT_REV_CFI000Type)/PreserveChanges">
                <Annotation Term="SAP__common.IsUpperCase"/>
                <Annotation Term="SAP__common.Label" String="TRUE"/>
                <Annotation Term="SAP__common.QuickInfo" String="Data element for domain BOOLE: TRUE (='X') and FALSE (=' ')"/>
            </Annotations>
            <Annotations Target="SAP__self.Edit(SAP__self.ZC_TBCAT_REV_CFI000Type)">
                <Annotation Term="SAP__core.OperationAvailable" Path="_it/__OperationControl/Edit"/>
            </Annotations>
            <Annotations Target="SAP__self.Container">
                <Annotation Term="SAP__common.ApplyMultiUnitBehaviorForSortingAndFiltering" Bool="true"/>
                <Annotation Term="SAP__UI.LeadingEntitySet" String="ZC_TBCAT_REV_CFI000"/>
                <Annotation Term="SAP__capabilities.FilterFunctions">
                    <Collection>
                        <String>eq</String>
                        <String>ne</String>
                        <String>gt</String>
                        <String>ge</String>
                        <String>lt</String>
                        <String>le</String>
                        <String>and</String>
                        <String>or</String>
                        <String>contains</String>
                        <String>startswith</String>
                        <String>endswith</String>
                        <String>any</String>
                        <String>all</String>
                    </Collection>
                </Annotation>
                <Annotation Term="SAP__capabilities.SupportedFormats">
                    <Collection>
                        <String>application/json</String>
                        <String>application/pdf</String>
                    </Collection>
                </Annotation>
                <Annotation Term="SAP__PDF.Features">
                    <Record>
                        <PropertyValue Property="DocumentDescriptionReference" String="../../../../default/iwbep/common/0001/$metadata"/>
                        <PropertyValue Property="DocumentDescriptionCollection" String="MyDocumentDescriptions"/>
                        <PropertyValue Property="ArchiveFormat" Bool="true"/>
                        <PropertyValue Property="Border" Bool="true"/>
                        <PropertyValue Property="CoverPage" Bool="true"/>
                        <PropertyValue Property="FitToPage" Bool="true"/>
                        <PropertyValue Property="FontName" Bool="true"/>
                        <PropertyValue Property="FontSize" Bool="true"/>
                        <PropertyValue Property="HeaderFooter" Bool="true"/>
                        <PropertyValue Property="IANATimezoneFormat" Bool="true"/>
                        <PropertyValue Property="Margin" Bool="true"/>
                        <PropertyValue Property="Padding" Bool="true"/>
                        <PropertyValue Property="ResultSizeDefault" Int="20000"/>
                        <PropertyValue Property="ResultSizeMaximum" Int="20000"/>
                        <PropertyValue Property="Signature" Bool="true"/>
                        <PropertyValue Property="TextDirectionLayout" Bool="true"/>
                        <PropertyValue Property="Treeview" Bool="true"/>
                        <PropertyValue Property="UploadToFileShare" Bool="true"/>
                    </Record>
                </Annotation>
                <Annotation Term="SAP__capabilities.KeyAsSegmentSupported"/>
                <Annotation Term="SAP__capabilities.AsynchronousRequestsSupported"/>
            </Annotations>
            <Annotations Target="SAP__self.I_DraftAdministrativeDataType/DraftUUID">
                <Annotation Term="SAP__UI.Hidden"/>
                <Annotation Term="SAP__common.Label" String="Draft (Technical ID)"/>
            </Annotations>
            <Annotations Target="SAP__self.I_DraftAdministrativeDataType/ProcessingStartDateTime">
                <Annotation Term="SAP__UI.Hidden"/>
                <Annotation Term="SAP__common.Label" String="Draft In Process Since"/>
            </Annotations>
            <Annotations Target="SAP__self.I_DraftAdministrativeDataType/DraftIsKeptByUser">
                <Annotation Term="SAP__UI.Hidden"/>
                <Annotation Term="SAP__common.Label" String="Draft Is Kept By User"/>
            </Annotations>
            <Annotations Target="SAP__self.I_DraftAdministrativeDataType/EnqueueStartDateTime">
                <Annotation Term="SAP__UI.Hidden"/>
                <Annotation Term="SAP__common.Label" String="Draft Locked Since"/>
            </Annotations>
            <Annotations Target="SAP__self.I_DraftAdministrativeDataType/DraftIsCreatedByMe">
                <Annotation Term="SAP__UI.Hidden"/>
                <Annotation Term="SAP__common.Label" String="Draft Created By Me"/>
            </Annotations>
            <Annotations Target="SAP__self.I_DraftAdministrativeDataType/DraftIsLastChangedByMe">
                <Annotation Term="SAP__UI.Hidden"/>
                <Annotation Term="SAP__common.Label" String="Draft Last Changed By Me"/>
            </Annotations>
            <Annotations Target="SAP__self.I_DraftAdministrativeDataType/DraftIsProcessedByMe">
                <Annotation Term="SAP__UI.Hidden"/>
                <Annotation Term="SAP__common.Label" String="Draft In Process By Me"/>
            </Annotations>
            <Annotations Target="SAP__self.I_DraftAdministrativeDataType/CreatedByUserDescription">
                <Annotation Term="SAP__UI.Hidden"/>
                <Annotation Term="SAP__common.Label" String="Draft Created By (Description)"/>
            </Annotations>
            <Annotations Target="SAP__self.I_DraftAdministrativeDataType/LastChangedByUserDescription">
                <Annotation Term="SAP__UI.Hidden"/>
                <Annotation Term="SAP__common.Label" String="Draft Last Changed By (Description)"/>
            </Annotations>
            <Annotations Target="SAP__self.I_DraftAdministrativeDataType/InProcessByUserDescription">
                <Annotation Term="SAP__UI.Hidden"/>
                <Annotation Term="SAP__common.Label" String="Draft In Process By (Description)"/>
            </Annotations>
            <Annotations Target="SAP__self.I_DraftAdministrativeDataType/CreationDateTime">
                <Annotation Term="SAP__common.Label" String="Draft Created On"/>
            </Annotations>
            <Annotations Target="SAP__self.I_DraftAdministrativeDataType/LastChangeDateTime">
                <Annotation Term="SAP__common.Label" String="Draft Last Changed On"/>
            </Annotations>
            <Annotations Target="SAP__self.ZC_TBCAT_REV_CFI000Type/Glaccount">
                <Annotation Term="SAP__common.Label" String="GLAccount"/>
            </Annotations>
            <Annotations Target="SAP__self.ZC_TBCAT_REV_CFI000Type/Posneg">
                <Annotation Term="SAP__common.Label" String="PosNeg"/>
            </Annotations>
            <Annotations Target="SAP__self.ZC_TBCAT_REV_CFI000Type/Amountintransactioncurrency">
                <Annotation Term="SAP__common.Label" String="AmountInTrans"/>
            </Annotations>
            <Annotations Target="SAP__self.ZC_TBCAT_REV_CFI000Type/Amountincompanycodecurrency">
                <Annotation Term="SAP__common.Label" String="AmountInCCode"/>
            </Annotations>
            <Annotations Target="SAP__self.ZC_TBCAT_REV_CFI000Type/Quantityinentryunit">
                <Annotation Term="SAP__common.Label" String="Quantity"/>
            </Annotations>
            <Annotations Target="SAP__self.ZC_TBCAT_REV_CFI000Type/Assignmentreference">
                <Annotation Term="SAP__common.Label" String="AssignmentReference"/>
            </Annotations>
            <Annotations Target="SAP__self.ZC_TBCAT_REV_CFI000Type/Housebank">
                <Annotation Term="SAP__common.Label" String="HouseBank"/>
            </Annotations>
            <Annotations Target="SAP__self.ZC_TBCAT_REV_CFI000Type/Housebankaccount">
                <Annotation Term="SAP__common.Label" String="HouseBank"/>
            </Annotations>
            <Annotations Target="SAP__self.ZC_TBCAT_REV_CFI000Type/Documentitemtext">
                <Annotation Term="SAP__common.Label" String="docheadtxt"/>
            </Annotations>
            <Annotations Target="SAP__self.ZC_TBCAT_REV_CFI000Type/Reference1idbybusinesspartner">
                <Annotation Term="SAP__common.Label" String="Reference1"/>
            </Annotations>
            <Annotations Target="SAP__self.ZC_TBCAT_REV_CFI000Type/Reference2idbybusinesspartner">
                <Annotation Term="SAP__common.Label" String="Reference1"/>
            </Annotations>
            <Annotations Target="SAP__self.ZC_TBCAT_REV_CFI000Type/Reference3idbybusinesspartner">
                <Annotation Term="SAP__common.Label" String="Reference3"/>
            </Annotations>
            <Annotations Target="SAP__self.ZC_TBCAT_REV_CFI000Type/Accountassignmenttype">
                <Annotation Term="SAP__common.Label" String="accountassignmenttyp"/>
                <Annotation Term="SAP__common.Heading" String="accountassignmenttype"/>
                <Annotation Term="SAP__common.QuickInfo" String="ACCOUNTASSIGN"/>
            </Annotations>
            <Annotations Target="SAP__self.ZC_TBCAT_REV_CFI000Type/Tariffcode">
                <Annotation Term="SAP__common.Label" String="Tariffcode"/>
            </Annotations>
            <Annotations Target="SAP__self.ZC_TBCAT_REV_CFI000Type/Lineofservice">
                <Annotation Term="SAP__common.Label" String="lineOfService"/>
            </Annotations>
            <Annotations Target="SAP__self.ZC_TBCAT_REV_CFI000Type/Ship">
                <Annotation Term="SAP__common.Label" String="ship"/>
            </Annotations>
            <Annotations Target="SAP__self.ZC_TBCAT_REV_CFI000Type/Paymentmethod">
                <Annotation Term="SAP__common.Label" String="PaymentMethod"/>
            </Annotations>
            <Annotations Target="SAP__self.ZC_TBCAT_REV_CFI000Type/Taxitemclassification">
                <Annotation Term="SAP__common.Label" String="taxitemclassificatio"/>
                <Annotation Term="SAP__common.Heading" String="taxitemclassification"/>
                <Annotation Term="SAP__common.QuickInfo" String="taxitemclassification"/>
            </Annotations>
            <Annotations Target="SAP__self.ZC_TBCAT_REV_CFI000OperationControl/Edit">
                <Annotation Term="SAP__common.Label" String="Dyn. Action Control"/>
                <Annotation Term="SAP__common.Heading" String="Dynamic Action Control"/>
                <Annotation Term="SAP__common.QuickInfo" String="Dynamic Action Property"/>
            </Annotations>
            <Annotations Target="SAP__self.EntityControl/Deletable">
                <Annotation Term="SAP__common.Label" String="Dyn. Method Control"/>
                <Annotation Term="SAP__common.Heading" String="Dynamic Method Control"/>
                <Annotation Term="SAP__common.QuickInfo" String="Dynamic Method Property"/>
            </Annotations>
            <Annotations Target="SAP__self.EntityControl/Updatable">
                <Annotation Term="SAP__common.Label" String="Dyn. Method Control"/>
                <Annotation Term="SAP__common.Heading" String="Dynamic Method Control"/>
                <Annotation Term="SAP__common.QuickInfo" String="Dynamic Method Property"/>
            </Annotations>
        </Schema>
    </edmx:DataServices>
</edmx:Edmx>